foran/__init__.py
foran/__main__.py
foran/cli.py
foran/foran.py
foran/render.py
foran/report.py
foran/status.py
foran-2023.6.19.dist-info/LICENSE
foran-2023.6.19.dist-info/METADATA
foran-2023.6.19.dist-info/WHEEL
foran-2023.6.19.dist-info/entry_points.txt
foran-2023.6.19.dist-info/top_level.txt
foran-2023.6.19.dist-info/RECORD
