Metadata-Version: 2.1
Name: foran
Version: 2023.6.19
Summary: In front or behind (Danish: foran eller bagved)? Answering the question if a local repository status is in front of or behind its remote.
Author-email: Stefan Hagen <stefan@hagen.link>
Maintainer-email: Stefan Hagen <stefan@hagen.link>
Project-URL: Homepage, https://git.sr.ht/~sthagen/foran
Project-URL: Bug-Tracker, https://todo.sr.ht/~sthagen/foran
Project-URL: Documentation, https://codes.dilettant.life/docs/foran
Project-URL: Source-Code, https://git.sr.ht/~sthagen/foran
Project-URL: Test-Coverage, https://codes.dilettant.life/coverage/foran
Keywords: git,developer-tools
Classifier: Development Status :: 3 - Alpha
Classifier: Intended Audience :: Developers
Classifier: License :: OSI Approved :: MIT License
Classifier: Programming Language :: Python :: 3.10
Classifier: Programming Language :: Python :: 3.11
Classifier: Programming Language :: Python :: 3.12
Classifier: Programming Language :: Python :: 3.9
Requires-Python: >=3.9
License-File: LICENSE
Requires-Dist: GitPython (>=3.1.31)
Requires-Dist: typer (>=0.9.0)
Provides-Extra: dev
Requires-Dist: black ; extra == 'dev'
Requires-Dist: coverage ; extra == 'dev'
Requires-Dist: hypothesis ; extra == 'dev'
Requires-Dist: mypy ; extra == 'dev'
Requires-Dist: pytest ; extra == 'dev'
Requires-Dist: pytest-cov ; extra == 'dev'
Requires-Dist: pytest-flake8 ; extra == 'dev'
Requires-Dist: ruff ; extra == 'dev'
